mimophys/__about__.py
mimophys/__init__.py
mimophys/network.py
mimophys/channels/__init__.py
mimophys/channels/awgn.py
mimophys/channels/los.py
mimophys/channels/multipath.py
mimophys/channels/ray_cluster.py
mimophys/channels/rayleigh.py
mimophys/channels/rician.py
mimophys/channels/spherical_wave.py
mimophys/channels/path_loss/__init__.py
mimophys/channels/path_loss/free_space.py
mimophys/channels/path_loss/get_path_loss.py
mimophys/channels/path_loss/path_loss.py
mimophys/devices/__init__.py
mimophys/devices/antenna_array.py
mimophys/plot/__init__.py
mimophys/plot/plot_arrays.py
mimophys/plot/plot_gains.py
mimophys/utils/__init__.py
mimophys/utils/geometry.py
mimophys-0.3.5.dist-info/METADATA
mimophys-0.3.5.dist-info/WHEEL
mimophys-0.3.5.dist-info/licenses/LICENSE
mimophys-0.3.5.dist-info/RECORD
