Metadata-Version: 2.4
Name: mimophys
Version: 0.3.5
Summary: A Python library for MIMO systems
Author-email: Samuel Li <samuel.li@ucla.edu>
License-Expression: MIT
License-File: LICENSE
Classifier: Development Status :: 3 - Alpha
Classifier: Intended Audience :: Science/Research
Classifier: Topic :: Scientific/Engineering
Requires-Python: >=3.10
Requires-Dist: matplotlib>=3.9
Requires-Dist: numpy>=1.26
Provides-Extra: dev
Requires-Dist: hatch>=1.14.1; extra == 'dev'
Requires-Dist: uv>=0.7.13; extra == 'dev'
